yaqd_fakes/__init__.py
yaqd_fakes/__version__.py
yaqd_fakes/_fake_camera.py
yaqd_fakes/_fake_continuous_hardware.py
yaqd_fakes/_fake_discrete_hardware.py
yaqd_fakes/_fake_furnace.py
yaqd_fakes/_fake_has_transformed_position.py
yaqd_fakes/_fake_has_turret.py
yaqd_fakes/_fake_sensor.py
yaqd_fakes/_fake_spectrometer.py
yaqd_fakes/_fake_triggered_sensor.py
yaqd_fakes/_signal_generators.py
yaqd_fakes/fake-camera.avpr
yaqd_fakes/fake-camera.toml
yaqd_fakes/fake-continuous-hardware.avpr
yaqd_fakes/fake-continuous-hardware.toml
yaqd_fakes/fake-discrete-hardware.avpr
yaqd_fakes/fake-discrete-hardware.toml
yaqd_fakes/fake-furnace.avpr
yaqd_fakes/fake-furnace.toml
yaqd_fakes/fake-has-transformed-position.avpr
yaqd_fakes/fake-has-transformed-position.toml
yaqd_fakes/fake-has-turret.avpr
yaqd_fakes/fake-has-turret.toml
yaqd_fakes/fake-sensor.avpr
yaqd_fakes/fake-sensor.toml
yaqd_fakes/fake-spectrometer.avpr
yaqd_fakes/fake-spectrometer.toml
yaqd_fakes/fake-triggered-sensor.avpr
yaqd_fakes/fake-triggered-sensor.toml
yaqd_fakes-2023.6.0.dist-info/METADATA
yaqd_fakes-2023.6.0.dist-info/WHEEL
yaqd_fakes-2023.6.0.dist-info/entry_points.txt
yaqd_fakes-2023.6.0.dist-info/licenses/LICENSE
yaqd_fakes-2023.6.0.dist-info/RECORD
