Metadata-Version: 2.1
Name: yaqd-fakes
Version: 2023.6.0
Project-URL: Home page, https://yaq.fyi
Project-URL: Source, https://github.com/yaq-project/yaq-python
Project-URL: Issues, https://github.com/yaq-project/yaq-python/issues
Author: yaq developers
License-Expression: LGPL-3.0-only
License-File: LICENSE
Classifier: Development Status :: 5 - Production/Stable
Classifier: Intended Audience :: Science/Research
Classifier: License :: OSI Approved :: GNU Lesser General Public License v3 (LGPLv3)
Classifier: Natural Language :: English
Classifier: Programming Language :: Python :: 3
Classifier: Programming Language :: Python :: 3.8
Classifier: Programming Language :: Python :: 3.9
Classifier: Programming Language :: Python :: 3.10
Classifier: Programming Language :: Python :: 3.11
Classifier: Topic :: Scientific/Engineering
Requires-Python: >=3.7
Requires-Dist: yaqd-core>=2022.3.0
Provides-Extra: dev
Requires-Dist: black; extra == 'dev'
Requires-Dist: pre-commit; extra == 'dev'
